sumonet/__init__.py
sumonet/data/__init__.py
sumonet/data/hard_test_samples/__init__.py
sumonet/data/hard_test_samples/hard_samples_negative.fasta
sumonet/data/hard_test_samples/hard_samples_positive.fasta
sumonet/data/test/Sumoylation_neg_Test.fasta
sumonet/data/test/Sumoylation_pos_Test.fasta
sumonet/data/test/__init__.py
sumonet/data/train/Sumoylation_neg_Train.fasta
sumonet/data/train/Sumoylation_pos_Train.fasta
sumonet/data/train/__init__.py
sumonet/evaluation/__init__.py
sumonet/evaluation/metrics.py
sumonet/model/__init__.py
sumonet/model/architecture.py
sumonet/model/pretrained/__init__.py
sumonet/model/pretrained/sumonet3.h5
sumonet/model/pretrained/sumonet3_partial.h5
sumonet/utils/__init__.py
sumonet/utils/data_pipe.py
sumonet/utils/encodings.py
sumonet/utils/encoding_matrix/__init__.py
sumonet/utils/encoding_matrix/blosum62.csv
sumonet/utils/scaler/__init__.py
sumonet/utils/scaler/minmax_scaler.gz
tests/__init__.py
tests/test_encodings.py
sumonet-0.1.6.dist-info/LICENSE.rst
sumonet-0.1.6.dist-info/METADATA
sumonet-0.1.6.dist-info/WHEEL
sumonet-0.1.6.dist-info/top_level.txt
sumonet-0.1.6.dist-info/RECORD
