Metadata-Version: 2.1
Name: sumonet
Version: 0.1.6
Summary: Package Description
Home-page: https://github.com/berkedilekoglu/SUMOnet
Download-URL: https://github.com/berkedilekoglu/SUMOnet/archive/refs/tags/v0.1.6tar.gz
Author: Berke Dilekoglu
Author-email: berkedilekoglu@sabanciuniv.edu
License: Academic Free License ("AFL") v. 3.0
Keywords: sumoylation machine-learning deep-learning bioinformatics
License-File: LICENSE.rst
Requires-Dist: numpy
Requires-Dist: scikit-learn
Requires-Dist: joblib
Requires-Dist: pandas
Requires-Dist: tensorflow
Requires-Dist: keras
Requires-Dist: requests
Requires-Dist: biopython
Requires-Dist: loguru
